{
	"class" : {
		"initializeWithOptions:objectMemoryClass:" : "eem 10/9/2013 15:30",
		"new" : "eem 9/3/2013 11:00",
		"newWithOptions:" : "eem 9/3/2013 11:01",
		"onObjectMemory:" : "eem 9/3/2013 11:01",
		"onObjectMemory:options:" : "eem 10/9/2013 13:05" },
	"instance" : {
		"allObjectsSelect:" : "eem 2/4/2014 11:15",
		"argumentCount:" : "eem 9/6/2013 13:31",
		"assertValidExecutionPointersAtEachStep" : "eem 5/28/2014 11:13",
		"assertValidExecutionPointersAtEachStep:" : "eem 5/28/2014 11:13",
		"baseFrameReturn" : "eem 2/27/2013 13:50",
		"booleanCheat:" : "eem 10/4/2010 15:57",
		"bootstrapping" : "eem 11/14/2013 16:20",
		"bootstrapping:" : "eem 11/14/2013 15:27",
		"browserPluginInitialiseIfNeeded" : "tpr 2/26/2003 14:07",
		"browserPluginReturnIfNeeded" : "tpr 2/26/2003 14:03",
		"byteAt:" : "eem 6/25/2011 12:34",
		"byteAt:put:" : "eem 6/25/2011 12:33",
		"byteCount" : "di 6/21/2004 15:05",
		"byteCountText" : "di 4/21/2004 00:09",
		"bytecodePrimAtPut" : "eem 2/7/2014 11:03",
		"cCoerce:to:" : "crl 3/3/2003 01:15",
		"cCoerceSimple:to:" : "eem 6/24/2008 15:38",
		"callExternalPrimitive:" : "eem 1/13/2009 11:16",
		"charsOfLong:" : "th 4/15/2000 17:22",
		"checkStackIntegrity" : "eem 9/20/2013 13:55",
		"classAndSelectorOfMethod:forReceiver:" : "eem 9/29/2010 17:44",
		"classNameOf:Is:" : "eem 8/17/2010 19:31",
		"clipboardRead:Into:At:" : "di 9/23/2001 12:26",
		"clipboardSize" : "di 9/23/2001 12:18",
		"clipboardWrite:From:At:" : "di 9/23/2001 17:36",
		"cloneSimulation" : "eem 5/27/2014 15:56",
		"cloneSimulationWindow" : "eem 5/25/2014 20:06",
		"close" : "eem 6/22/2011 12:06",
		"convertToArray" : "eem (objmem refactor) 6/8/2010 17:12",
		"copyBits" : "",
		"cr" : "eem 6/20/2008 15:46",
		"createActualMessageTo:" : "eem 1/17/2014 15:51",
		"desiredDisplayExtent" : "eem 5/11/2011 16:58",
		"desiredEdenBytes:" : "eem 3/10/2009 08:59",
		"desiredNumStackPages:" : "eem 3/10/2009 08:58",
		"disableBooleanCheat:" : "eem 10/4/2010 15:54",
		"dispatchMappedPluginEntry:" : "eem 10/8/2013 16:44",
		"dispatchOn:in:" : "eem 11/12/2012 22:37",
		"displayForm" : "tty 2/5/2014 12:44",
		"displayLocation" : "",
		"displayView" : "tty 2/5/2014 12:45",
		"displayView:" : "tty 2/5/2014 12:45",
		"divorceFramesIn:" : "eem 6/28/2008 17:06",
		"doSignalExternalSemaphores:" : "eem 9/23/2009 14:33",
		"doesNotUnderstand:" : "eem 6/27/2012 20:14",
		"drawLoopX:Y:" : "",
		"dumpMethodHeader:" : "",
		"elementsPerPrintOopLine" : "eem 6/20/2008 15:25",
		"ensureDebugAtEachStepBlock" : "eem 10/2/2010 15:45",
		"externalDivorceFrame:andContext:" : "eem 6/28/2008 17:06",
		"externalInstVar:ofContext:put:" : "eem 2/27/2013 13:50",
		"externalWriteBackHeadFramePointers" : "eem 9/17/2009 09:14",
		"fetchByte" : "",
		"filterPerformOf:to:" : "eem 1/11/2013 18:38",
		"findNewMethodInClassTag:" : "eem 9/11/2013 19:06",
		"firstIndexableField:" : "eem 6/11/2010 11:36",
		"flush" : "eem 2/10/2009 15:46",
		"flushExternalPrimitives" : "eem 1/6/2014 09:47",
		"forShortPrintString:filterPerformMessages:" : "eem 1/11/2013 18:33",
		"frameOfMarriedContext:" : "eem (objmem refactor) 6/8/2010 17:12",
		"framePointer" : "eem 9/18/2013 11:32",
		"fullDisplay" : "eem (objmem refactor) 6/8/2010 17:12",
		"fullDisplayUpdate" : "eem 11/25/2008 13:32",
		"functionPointerFor:inClass:" : "eem 6/24/2008 16:00",
		"getErrorObjectFromPrimFailCode" : "eem 11/26/2008 12:36",
		"getLongFromFile:swap:" : "eem 10/10/2013 06:25",
		"getShortFromFile:swap:" : "eem 10/10/2013 06:23",
		"halfWordHighInLong32:" : "di 7/16/2004 14:56",
		"halfWordLowInLong32:" : "di 7/16/2004 14:57",
		"headerStart:" : "eem (objmem refactor) 6/8/2010 17:12",
		"imageName" : "eem 9/19/2013 15:46",
		"imageName:" : "eem 9/19/2013 15:47",
		"imageNameGet:Length:" : "eem 10/8/2013 16:37",
		"imageNamePut:Length:" : "eem 10/8/2013 22:43",
		"imageNameSize" : "eem 10/8/2013 16:36",
		"incrementByteCount" : "eem 3/14/2014 16:40",
		"initialize" : "EstebanLorenzano 6/16/2014 10:37",
		"instVar:ofContext:put:" : "eem 2/27/2013 13:50",
		"insufficientMemoryAvailableError" : "tpr 2/26/2003 14:01",
		"insufficientMemorySpecifiedError" : "tpr 2/26/2003 14:01",
		"integerAt:" : "eem (objmem refactor) 6/8/2010 17:12",
		"integerAt:put:" : "eem (objmem refactor) 6/8/2010 17:12",
		"internalCannotReturn:" : "eem 6/27/2008 14:13",
		"internalFindNewMethod" : "eem 9/9/2013 17:50",
		"internalMustBeBoolean" : "eem 6/27/2008 14:13",
		"interpreterAllocationReserveBytes" : "eem 11/14/2013 15:01",
		"invalidCompactClassError:" : "eem 12/30/2008 12:28",
		"ioCanRenameImage" : "ar 2/5/2001 18:33",
		"ioCanWriteImage" : "ar 2/5/2001 20:42",
		"ioExit" : "ajh 8/21/2002 22:41",
		"ioExitWithErrorCode:" : "eem 6/23/2010 11:20",
		"ioForceDisplayUpdate" : "ikp 12/15/1998 23:33",
		"ioGetMaxExtSemTableSize" : "eem 2/3/2010 12:56",
		"ioGetNextEvent:" : "tty 2/13/2014 17:33",
		"ioHasDisplayDepth:" : "ar 5/1/1999 09:43",
		"ioHeartbeatMilliseconds" : "eem 8/22/2008 11:18",
		"ioInitHeartbeat" : "eem 8/3/2008 21:48",
		"ioLoadFunction:From:" : "eem 10/12/2009 00:58",
		"ioLoadFunction:From:AccessorDepthInto:" : "eem 5/4/2014 16:08",
		"ioMSecs" : "eem 12/10/2009 14:53",
		"ioMicroMSecs" : "jm 3/9/1999 10:00",
		"ioProcessEvents" : "",
		"ioRelinquishProcessorForMicroseconds:" : "EstebanLorenzano 6/2/2014 17:08",
		"ioScreenDepth" : "ar 2/5/2001 17:24",
		"ioScreenSize" : "jm 9/24/97 22:52",
		"ioSetInputSemaphore:" : "yo 2/14/2001 14:17",
		"ioSetMaxExtSemTableSize:" : "eem 2/3/2010 12:57",
		"ioSynchronousCheckForEvents" : "eem 2/4/2010 09:37",
		"ioUTCMicroseconds" : "eem 8/21/2009 15:03",
		"isPrimitiveFunctionPointerAnIndex" : "eem 7/9/2008 18:58",
		"isThreadedVM" : "eem 10/12/2009 01:18",
		"isWidowedContext:" : "eem 9/30/2010 13:37",
		"literal:" : "eem 11/5/2013 17:53",
		"loadNewPlugin:" : "eem 5/4/2014 16:09",
		"localFP" : "eem 9/6/2013 13:30",
		"localIP" : "eem 9/6/2013 13:51",
		"localIP:" : "eem 9/6/2013 14:04",
		"localSP" : "eem 9/16/2013 01:07",
		"logOfBytesVerify:fromFileNamed:fromStart:" : "eem 6/26/2012 09:19",
		"logOfBytesWrite:toFileNamed:fromStart:" : "eem 6/26/2012 09:20",
		"logOfSendsVerify:fromFileNamed:fromStart:" : "eem 10/14/2009 15:24",
		"logOfSendsWrite:toFileNamed:fromStart:" : "eem 10/14/2009 09:23",
		"longAt:" : "eem 6/25/2011 12:11",
		"longAt:put:" : "eem 6/25/2011 12:11",
		"makeDirEntryName:size:createDate:modDate:isDir:fileSize:posixPermissions:" : "",
		"makeDirEntryName:size:createDate:modDate:isDir:fileSize:posixPermissions:isSymlink:" : "EstebanLorenzano 8/2/2012 14:15",
		"markContextAsDead:" : "eem 11/8/2013 17:00",
		"messageSelector:" : "eem 9/12/2013 10:18",
		"methodForContext:" : "eem 2/27/2013 13:50",
		"nameOfClass:" : "eem 10/18/2013 14:20",
		"nextLongFrom:" : "th 4/15/2000 17:19",
		"nextShortFrom:" : "eem 10/9/2008 16:37",
		"openAsMorph" : "StefanMarr 2/12/2014 13:51",
		"openAsMorphNoTranscript" : "StefanMarr 2/12/2014 13:52",
		"openAsStackInterpreterSimulatorMorph" : "tty 2/5/2014 12:19",
		"openOn:extraMemory:" : "eem 4/9/2014 10:14",
		"parent" : "eem 5/24/2014 23:38",
		"parent:" : "eem 5/24/2014 23:38",
		"preBecomeAction" : "eem 1/17/2014 19:03",
		"preGCAction:" : "eem 8/4/2011 15:36",
		"primBitmapcompresstoByteArray" : "di 6/29/1998 22:17",
		"primBitmapdecompressfromByteArrayat" : "eem (objmem refactor) 6/8/2010 17:12",
		"primStringcomparewithcollated" : "di 6/29/1998 22:17",
		"primStringfindSubstringinstartingAtmatchTable" : "ikp 12/15/1998 23:30",
		"primStringindexOfAsciiinStringstartingAt" : "di 11/8/1998 13:04",
		"primStringtranslatefromtotable" : "yo 1/29/1999 21:37",
		"primitiveAtPut" : "eem 9/13/2013 16:45",
		"primitiveBeDisplay" : "eem (objmem refactor) 6/8/2010 17:12",
		"primitiveBeep" : "",
		"primitiveContextAt" : "eem 6/27/2008 16:27",
		"primitiveDirectoryEntry" : "GuillermoPolito 6/17/2013 15:29",
		"primitiveDirectoryLookup" : "GuillermoPolito 6/17/2013 15:29",
		"primitiveDoPrimitiveWithArgs" : "eem 12/19/2012 09:49",
		"primitiveExecuteMethod" : "eem 9/30/2013 13:10",
		"primitiveExecuteMethodArgsArray" : "eem 1/17/2014 10:08",
		"primitiveFailFor:" : "eem 12/4/2008 12:58",
		"primitiveGetAttribute" : "eem 2/13/2014 09:35",
		"primitiveIdentityHash" : "eem 9/22/2013 07:56",
		"primitiveKbdNext" : "eem (objmem refactor) 6/8/2010 17:12",
		"primitiveKbdPeek" : "eem (objmem refactor) 6/8/2010 17:12",
		"primitiveMouseButtons" : "di 9/23/97 12:54",
		"primitiveMousePoint" : "di 4/21/2004 00:21",
		"primitiveNewWithArg" : "eem 2/11/2014 17:05",
		"primitiveObject:perform:withArguments:lookedUpIn:" : "eem 1/11/2013 18:38",
		"primitiveObjectPointsTo" : "eem 2/5/2014 18:31",
		"primitivePerform" : "eem 9/17/2013 12:49",
		"primitiveStoreStackp" : "eem 6/22/2010 11:06",
		"primitiveSuspend" : "eem 6/25/2008 09:25",
		"primitiveWait" : "eem 6/25/2008 09:24",
		"print:" : "eem 6/20/2008 17:39",
		"printChar:" : "di 5/11/2004 18:28",
		"printCurrentBytecodeOn:" : "eem 6/26/2012 09:20",
		"printECS" : "eem 7/4/2008 15:02",
		"printFrameFlagsForFP:" : "eem 6/22/2010 14:46",
		"printFrameOop:at:" : "eem 6/22/2010 14:42",
		"printFrameThing:andFrame:at:" : "eem 10/29/2013 16:05",
		"printFrameThing:at:" : "eem 6/22/2010 14:44",
		"printHex:" : "eem 7/11/2008 13:29",
		"printHexnp:" : "eem 9/21/2013 06:19",
		"printLCS" : "eem 7/4/2008 15:02",
		"printNum:" : "eem 7/7/2008 16:45",
		"printStringForCurrentBytecode" : "eem 7/1/2008 09:24",
		"printStringOf:" : "eem 10/12/2009 01:03",
		"profile:" : "di 5/11/2004 18:28",
		"profileSends:" : "di 11/29/2000 10:25",
		"pushMaybeContextReceiverVariable:" : "eem 6/30/2008 15:04",
		"queueForwardedEvent:" : "tty 2/5/2014 16:17",
		"reverseBytesInImage" : "eem 4/18/2009 20:33",
		"rewriteMethodCacheEntryForExternalPrimitiveToFunction:" : "eem 6/20/2009 11:33",
		"run" : "eem 3/17/2014 10:38",
		"runAtEachStep:" : "eem 8/3/2008 21:52",
		"runAtEachStep:breakCount:" : "eem 8/3/2008 21:52",
		"runForNBytes:" : "eem 8/3/2008 21:54",
		"runWithBreakCount:" : "eem 9/23/2013 10:22",
		"savedWindowSize" : "eem 10/11/2013 09:56",
		"sendBreak:point:receiver:" : "eem 6/25/2011 12:47",
		"setDisplayForm:" : "eem 10/11/2013 10:06",
		"shortPrint:" : "eem 3/19/2014 17:21",
		"shortPrintContext:" : "eem 12/3/2010 07:23",
		"shortPrintFrame:" : "eem 10/11/2013 12:37",
		"showDisplayBits:w:h:d:left:right:top:bottom:" : "eem (objmem refactor) 6/8/2010 17:12",
		"signalSemaphoreWithIndex:" : "eem 9/23/2009 14:29",
		"singleStep" : "eem 9/18/2013 12:37",
		"space" : "eem 6/20/2008 15:21",
		"sqGetInterpreterProxy" : "ar 5/11/2000 21:47",
		"sqMemoryExtraBytesLeft:" : "ar 2/25/2001 17:16",
		"sqShrinkMemory:By:" : "di 5/11/2004 18:29",
		"stackPage" : "eem 9/17/2013 15:16",
		"stackPages" : "eem 11/2/2013 01:12",
		"startInContextSuchThat:" : "eem 11/13/2012 17:33",
		"startInSender" : "eem 11/12/2012 21:53",
		"startOfMemory" : "eem 10/9/2013 14:39",
		"success:" : "eem 12/4/2008 12:57",
		"systemAttributes" : "eem 1/16/2014 11:40",
		"tab" : "eem 6/20/2008 17:05",
		"test" : "eem 10/3/2010 08:25",
		"test1" : "eem 10/3/2010 08:25",
		"testBecome" : "eem (objmem refactor) 6/8/2010 17:12",
		"testBreakCount:printSends:printFrames:printBytecodes:" : "eem 10/19/2009 11:35",
		"testWithFramePrint" : "eem 6/25/2008 12:15",
		"toggleTranscript" : "eem 10/2/2010 15:31",
		"toggleTranscriptForSimulatorMorph:" : "tty 2/5/2014 12:19",
		"transcript" : "eem 10/12/2009 01:05",
		"transcript:" : "eem 7/18/2010 18:28",
		"transferTo:" : "eem 7/1/2008 13:27",
		"unableToReadImageError" : "tpr 2/26/2003 14:00",
		"updateStateOfSpouseContextForFrame:WithSP:" : "eem 7/6/2008 22:36",
		"utilitiesMenu:" : "eem 5/25/2014 20:04",
		"validOop:" : "eem (objmem refactor) 6/8/2010 17:12",
		"vmPathGet:Length:" : "eem (objmem refactor) 6/8/2010 17:12",
		"vmPathSize" : "",
		"warning:" : "eem 10/12/2009 01:03",
		"warpBits" : "yo 6/3/1999 16:10",
		"withMemoryProtectionDo:" : "eem 7/3/2008 11:02",
		"withSmallIntegerTags:" : "eem 6/20/2008 13:37",
		"withoutSmallIntegerTags:" : "eem 6/23/2008 13:57",
		"writeEnableMemory" : "eem (objmem refactor) 6/8/2010 17:12",
		"writeProtectMemory" : "eem (objmem refactor) 6/8/2010 17:12" } }
