{
	"class" : {
		 },
	"instance" : {
		"addDriver:sources:generator:" : "DavidGraham 3/26/2011 05:08",
		"addVMDrivers:" : "DavidGraham 3/25/2011 21:09",
		"compilerFlags" : "DavidGraham 3/26/2011 04:57",
		"compilerFlagsDebug" : "EstebanLorenzano 3/12/2014 16:09",
		"compilerFlagsRelease" : "EstebanLorenzano 3/12/2014 16:03",
		"configH" : "DavidGraham 3/25/2011 21:22",
		"configureFloatMathPlugin:" : "DavidGraham 3/25/2011 18:13",
		"setExtraTargetProperties:" : "DavidGraham 3/26/2011 03:36" } }
