{
	"category" : "VMMaker-InterpreterSimulation",
	"classinstvars" : [
		 ],
	"classvars" : [
		 ],
	"commentStamp" : "eem 9/3/2013 11:05",
	"instvars" : [
		"byteCount",
		"breakCount",
		"sendCount",
		"printSends",
		"printReturns",
		"traceOn",
		"myBitBlt",
		"displayForm",
		"filesOpen",
		"imageName",
		"pluginList",
		"mappedPluginEntries",
		"quitBlock",
		"transcript",
		"displayView",
		"printFrameAtEachStep",
		"printBytecodeAtEachStep",
		"startMicroseconds",
		"externalSemaphoreSignalRequests",
		"externalSemaphoreSignalResponses",
		"extSemTabSize",
		"atEachStepBlock",
		"disableBooleanCheat" ],
	"name" : "StackInterpreterSimulator",
	"pools" : [
		 ],
	"super" : "StackInterpreterPrimitives",
	"type" : "normal" }
