{
	"class" : {
		 },
	"instance" : {
		"assertCheckLongArithOpCodeSize:" : "lw 7/31/2012 15:02",
		"assertCheckQuickArithOpCodeSize:" : "lw 7/31/2012 14:25",
		"concreteCompilerClass" : "lw 7/16/2012 12:01",
		"disassembleInstructionAt:In:into:" : "eem 9/17/2015 10:04",
		"memoryAsBytes:" : "eem 11/13/2015 11:22",
		"objectMemory" : "eem 11/13/2015 10:06",
		"processor" : "lw 7/16/2012 12:02",
		"strip:" : "tpr 4/24/2014 17:24",
		"testAdd" : "eem 12/03/2015 18:26",
		"testGenerateMul" : "tpr 3/23/2015 18:00",
		"testMoveCwR" : "eem 11/13/2015 11:18",
		"testPerformAdd" : "eem 11/13/2015 11:34",
		"testPrefetchAw" : "eem 12/03/2015 18:26",
		"testPushR" : "eem 12/03/2015 18:26",
		"testRetN" : "eem 12/03/2015 18:26",
		"wordSize" : "eem 11/13/2015 10:07" } }
