{
	"class" : {
		 },
	"instance" : {
		"addImmediateUnsigned:" : "rmacnak 11/10/2015 21:04:27",
		"addUnsigned:" : "rmacnak 11/10/2015 21:04:31",
		"andImmediate:" : "rmacnak 11/10/2015 21:04:36",
		"bitwiseAnd:" : "rmacnak 11/10/2015 21:04:39",
		"bitwiseOr:" : "rmacnak 11/10/2015 21:04:42",
		"bitwiseXor:" : "rmacnak 11/10/2015 21:04:46",
		"branchEqual:" : "rmacnak 11/10/2015 21:06:31",
		"branchGreaterEqualZero:" : "rmacnak 11/10/2015 21:07:34",
		"branchGreaterThanZero:" : "rmacnak 11/10/2015 21:07:37",
		"branchLessEqualZero:" : "rmacnak 11/10/2015 21:07:42",
		"branchLessThanZero:" : "rmacnak 11/10/2015 21:07:45",
		"branchNotEqual:" : "rmacnak 11/10/2015 21:07:48",
		"break:" : "rmacnak 11/10/2015 21:06:54",
		"disassemble:from:to:" : "rmacnak 11/10/2015 21:21:25",
		"disassemble:from:to:for:labels:on:" : "rmacnak 11/15/2015 16:02:25",
		"divideSigned:" : "rmacnak 11/21/2015 18:18:00",
		"jump:" : "rmacnak 11/10/2015 21:06:59",
		"jumpAndLink:" : "rmacnak 11/10/2015 21:07:02",
		"jumpAndLinkRegister:" : "rmacnak 11/10/2015 21:13:26",
		"jumpRegister:" : "rmacnak 11/10/2015 21:07:11",
		"loadByte:" : "rmacnak 11/10/2015 21:08:36",
		"loadByteUnsigned:" : "rmacnak 11/10/2015 21:08:38",
		"loadHalfword:" : "rmacnak 11/10/2015 21:08:42",
		"loadHalfwordUnsigned:" : "rmacnak 11/10/2015 21:08:46",
		"loadUpperImmediate:" : "rmacnak 11/10/2015 21:07:16",
		"loadWord:" : "rmacnak 11/10/2015 21:08:49",
		"moveFromHigh:" : "rmacnak 11/21/2015 18:20:26",
		"moveFromLow:" : "rmacnak 11/21/2015 18:20:34",
		"multiplySigned:" : "rmacnak 11/21/2015 18:18:33",
		"orImmediate:" : "rmacnak 11/10/2015 21:04:51",
		"prefetch:" : "rmacnak 11/16/2015 20:48:27",
		"setOnLessThan:" : "rmacnak 11/10/2015 21:04:55",
		"setOnLessThanImmediate:" : "rmacnak 11/10/2015 21:04:58",
		"setOnLessThanImmediateUnsigned:" : "rmacnak 11/10/2015 21:05:04",
		"setOnLessThanUnsigned:" : "rmacnak 11/10/2015 23:10:29",
		"shiftLeftLogical:" : "rmacnak 11/10/2015 21:05:13",
		"shiftLeftLogicalVariable:" : "rmacnak 11/10/2015 21:05:21",
		"shiftRightArithmetic:" : "rmacnak 11/10/2015 21:05:24",
		"shiftRightArithmeticVariable:" : "rmacnak 11/10/2015 21:05:26",
		"shiftRightLogical:" : "rmacnak 11/10/2015 21:05:29",
		"shiftRightLogicalVariable:" : "rmacnak 11/10/2015 21:05:34",
		"storeByte:" : "rmacnak 11/10/2015 21:08:52",
		"storeHalfword:" : "rmacnak 11/10/2015 21:08:55",
		"storeWord:" : "rmacnak 11/10/2015 21:08:58",
		"subtractUnsigned:" : "rmacnak 11/10/2015 21:05:37",
		"xorImmediate:" : "rmacnak 11/10/2015 21:05:41" } }
